ceeteem/__init__.py
ceeteem/auth.py
ceeteem/py.typed
ceeteem/session.py
ceeteem-0.0.4.dist-info/METADATA
ceeteem-0.0.4.dist-info/WHEEL
ceeteem-0.0.4.dist-info/licenses/LICENSE
ceeteem-0.0.4.dist-info/licenses/LICENSE-requests.txt
ceeteem-0.0.4.dist-info/RECORD
