Metadata-Version: 2.4
Name: ceeteem
Version: 0.0.4
Summary: Token-aware Python client for the Control-M/Helix Automation API
Project-URL: Homepage, https://github.com/coparaoji/ceeteem
Project-URL: Docs, https://coparaoji.github.io/ceeteem
Project-URL: Issues, https://github.com/coparaoji/ceeteem/issues
Author-email: coparaoji <coparaoji@gmail.com>
License-Expression: GPL-3.0-or-later
License-File: LICENSE
License-File: LICENSE-requests.txt
Requires-Python: >=3.10
Requires-Dist: requests>=2.32.3
